graphene_django_tools/__init__.py
graphene_django_tools/connection.py
graphene_django_tools/dataloader.py
graphene_django_tools/global_id.py
graphene_django_tools/model_type.py
graphene_django_tools/queryset.py
graphene_django_tools/resolver.py
graphene_django_tools-0.21.0.dist-info/LICENSE
graphene_django_tools-0.21.0.dist-info/WHEEL
graphene_django_tools-0.21.0.dist-info/METADATA
graphene_django_tools-0.21.0.dist-info/RECORD
