Metadata-Version: 2.1
Name: graphene-django-tools
Version: 0.21.0
Summary: Tools for use [`graphene-django`](https://github.com/graphql-python/graphene-django)
Home-page: https://github.com/NateScarlet/graphene-django-tools
License: MIT
Keywords: graphene,django,graphql
Author: NateScarlet
Author-email: NateScarlet@Gmail.com
Requires-Python: >=3.6,<4.0
Classifier: Framework :: Django :: 2.1
Classifier: Framework :: Django :: 2.2
Classifier: Framework :: Django :: 3.0
Classifier: Intended Audience :: Developers
Classifier: License :: OSI Approved :: MIT License
Classifier: Programming Language :: Python :: 3
Classifier: Programming Language :: Python :: 3.6
Classifier: Programming Language :: Python :: 3.7
Classifier: Programming Language :: Python :: 3.8
Classifier: Topic :: Software Development :: Libraries :: Python Modules
Requires-Dist: graphene (>=2.1,<3.0)
Requires-Dist: graphene-resolver (>=0.1.9,<0.2.0)
Requires-Dist: isodate (>=0.6,<0.7)
Requires-Dist: lazy-object-proxy (>=1.4,<2.0)
Project-URL: Documentation, https://github.com/NateScarlet/graphene-django-tools/tree/master/docs
Project-URL: Repository, https://github.com/NateScarlet/graphene-django-tools
